dicomhandler/__init__.py
dicomhandler/dicom_info.py
dicomhandler/report.py
dicomhandler-0.0.1.dist-info/LICENSE
dicomhandler-0.0.1.dist-info/METADATA
dicomhandler-0.0.1.dist-info/WHEEL
dicomhandler-0.0.1.dist-info/top_level.txt
dicomhandler-0.0.1.dist-info/RECORD
