Metadata-Version: 2.1
Name: dicomhandler
Version: 0.0.1
Summary: dicomhandler is a package for wrapping many pydicom objects of the same patient, performing transformations in structures and comparing them with the originals.
Author-email: Jerónimo Fotinós <jerofoti@gmail.com>, Alejandro Rojas <alexrojas@ciencias.unam.mx>, Nicola Maddalozzo <nicolamaddalozzo95@gmail.com>
License: MIT License
Project-URL: Homepage, https://github.com/alxrojas/dicom2handle
Project-URL: Repository, https://github.com/alxrojas/dicom2handle
Keywords: dicomhandler,dicom,dcm,cancer,radiotherapy
Classifier: Intended Audience :: Education
Classifier: Intended Audience :: Science/Research
Classifier: Operating System :: OS Independent
Classifier: Programming Language :: Python
Classifier: Programming Language :: Python :: 3.10
Classifier: Programming Language :: Python :: Implementation :: CPython
Classifier: Topic :: Scientific/Engineering
Requires-Python: >=3.7
License-File: LICENSE
Requires-Dist: numpy
Requires-Dist: pandas
Requires-Dist: pydicom
Requires-Dist: toml
